{
  "contentTypes": [
    {
      "sys": {
        "space": {
          "sys": {
            "type": "Link",
            "linkType": "Space",
            "id": "myhn7g87ffcm"
          }
        },
        "id": "post",
        "type": "ContentType",
        "createdAt": "2024-08-22T23:35:32.266Z",
        "updatedAt": "2024-08-23T00:00:06.263Z",
        "environment": {
          "sys": {
            "id": "master",
            "type": "Link",
            "linkType": "Environment"
          }
        },
        "publishedVersion": 17,
        "publishedAt": "2024-08-23T00:00:06.263Z",
        "firstPublishedAt": "2024-08-22T23:35:32.940Z",
        "createdBy": {
          "sys": {
            "type": "Link",
            "linkType": "User",
            "id": "69J9p6yQN9sFQFqs3m7Byv"
          }
        },
        "updatedBy": {
          "sys": {
            "type": "Link",
            "linkType": "User",
            "id": "69J9p6yQN9sFQFqs3m7Byv"
          }
        },
        "publishedCounter": 9,
        "version": 18,
        "publishedBy": {
          "sys": {
            "type": "Link",
            "linkType": "User",
            "id": "69J9p6yQN9sFQFqs3m7Byv"
          }
        },
        "urn": "crn:contentful:::content:spaces/myhn7g87ffcm/environments/master/content_types/post"
      },
      "displayField": "title",
      "name": "Post",
      "description": "",
      "fields": [
        {
          "id": "title",
          "name": "Title",
          "type": "Symbol",
          "localized": false,
          "required": false,
          "validations": [
          ],
          "disabled": false,
          "omitted": true
        },
        {
          "id": "content",
          "name": "Content",
          "type": "RichText",
          "localized": false,
          "required": true,
          "validations": [
            {
              "enabledMarks": [
                "bold",
                "italic",
                "underline",
                "superscript",
                "subscript",
                "strikethrough",
                "code"
              ],
              "message": "Only bold, italic, underline, superscript, subscript, strikethrough, and code marks are allowed"
            },
            {
              "enabledNodeTypes": [
                "heading-1",
                "heading-2",
                "heading-3",
                "heading-4",
                "heading-5",
                "heading-6",
                "ordered-list",
                "unordered-list",
                "hr",
                "blockquote",
                "table",
                "hyperlink"
              ],
              "message": "Only heading 1, heading 2, heading 3, heading 4, heading 5, heading 6, ordered list, unordered list, horizontal rule, quote, table, and link to Url nodes are allowed"
            },
            {
              "nodes": {
              }
            }
          ],
          "disabled": false,
          "omitted": false
        },
        {
          "id": "likedBy",
          "name": "Liked By",
          "type": "Array",
          "localized": false,
          "required": false,
          "validations": [
          ],
          "disabled": false,
          "omitted": false,
          "items": {
            "type": "Link",
            "validations": [
              {
                "linkContentType": [
                  "user"
                ]
              }
            ],
            "linkType": "Entry"
          }
        },
        {
          "id": "comments",
          "name": "Comments",
          "type": "Array",
          "localized": false,
          "required": false,
          "validations": [
          ],
          "disabled": false,
          "omitted": false,
          "items": {
            "type": "Link",
            "validations": [
              {
                "linkContentType": [
                  "comment"
                ]
              }
            ],
            "linkType": "Entry"
          }
        }
      ]
    },
    {
      "sys": {
        "space": {
          "sys": {
            "type": "Link",
            "linkType": "Space",
            "id": "myhn7g87ffcm"
          }
        },
        "id": "comment",
        "type": "ContentType",
        "createdAt": "2024-08-22T23:37:51.067Z",
        "updatedAt": "2024-08-22T23:58:59.209Z",
        "environment": {
          "sys": {
            "id": "master",
            "type": "Link",
            "linkType": "Environment"
          }
        },
        "publishedVersion": 7,
        "publishedAt": "2024-08-22T23:58:59.209Z",
        "firstPublishedAt": "2024-08-22T23:37:51.432Z",
        "createdBy": {
          "sys": {
            "type": "Link",
            "linkType": "User",
            "id": "69J9p6yQN9sFQFqs3m7Byv"
          }
        },
        "updatedBy": {
          "sys": {
            "type": "Link",
            "linkType": "User",
            "id": "69J9p6yQN9sFQFqs3m7Byv"
          }
        },
        "publishedCounter": 4,
        "version": 8,
        "publishedBy": {
          "sys": {
            "type": "Link",
            "linkType": "User",
            "id": "69J9p6yQN9sFQFqs3m7Byv"
          }
        },
        "urn": "crn:contentful:::content:spaces/myhn7g87ffcm/environments/master/content_types/comment"
      },
      "displayField": null,
      "name": "Comment",
      "description": "",
      "fields": [
        {
          "id": "content",
          "name": "Content",
          "type": "RichText",
          "localized": false,
          "required": true,
          "validations": [
            {
              "enabledMarks": [
              ],
              "message": "Marks are not allowed"
            },
            {
              "enabledNodeTypes": [
                "hyperlink"
              ],
              "message": "Only link to Url nodes are allowed"
            },
            {
              "nodes": {
              }
            }
          ],
          "disabled": false,
          "omitted": false
        },
        {
          "id": "author",
          "name": "Author",
          "type": "Link",
          "localized": false,
          "required": true,
          "validations": [
            {
              "linkContentType": [
                "user"
              ]
            }
          ],
          "disabled": false,
          "omitted": false,
          "linkType": "Entry"
        },
        {
          "id": "likedBy",
          "name": "Liked By",
          "type": "Array",
          "localized": false,
          "required": false,
          "validations": [
          ],
          "disabled": false,
          "omitted": false,
          "items": {
            "type": "Link",
            "validations": [
              {
                "linkContentType": [
                  "user"
                ]
              }
            ],
            "linkType": "Entry"
          }
        }
      ]
    },
    {
      "sys": {
        "space": {
          "sys": {
            "type": "Link",
            "linkType": "Space",
            "id": "myhn7g87ffcm"
          }
        },
        "id": "user",
        "type": "ContentType",
        "createdAt": "2024-08-22T23:38:49.879Z",
        "updatedAt": "2024-08-23T04:17:42.039Z",
        "environment": {
          "sys": {
            "id": "master",
            "type": "Link",
            "linkType": "Environment"
          }
        },
        "publishedVersion": 23,
        "publishedAt": "2024-08-23T04:17:42.039Z",
        "firstPublishedAt": "2024-08-22T23:38:50.298Z",
        "createdBy": {
          "sys": {
            "type": "Link",
            "linkType": "User",
            "id": "69J9p6yQN9sFQFqs3m7Byv"
          }
        },
        "updatedBy": {
          "sys": {
            "type": "Link",
            "linkType": "User",
            "id": "69J9p6yQN9sFQFqs3m7Byv"
          }
        },
        "publishedCounter": 12,
        "version": 24,
        "publishedBy": {
          "sys": {
            "type": "Link",
            "linkType": "User",
            "id": "69J9p6yQN9sFQFqs3m7Byv"
          }
        },
        "urn": "crn:contentful:::content:spaces/myhn7g87ffcm/environments/master/content_types/user"
      },
      "displayField": "name",
      "name": "User",
      "description": "",
      "fields": [
        {
          "id": "id",
          "name": "Id",
          "type": "Symbol",
          "localized": false,
          "required": true,
          "validations": [
          ],
          "disabled": false,
          "omitted": false
        },
        {
          "id": "name",
          "name": "Name",
          "type": "Symbol",
          "localized": false,
          "required": true,
          "validations": [
          ],
          "disabled": false,
          "omitted": false
        },
        {
          "id": "email",
          "name": "Email",
          "type": "Symbol",
          "localized": false,
          "required": true,
          "validations": [
            {
              "regexp": {
                "pattern": "^\\w[\\w.-]*@([\\w-]+\\.)+[\\w-]+$",
                "flags": null
              }
            }
          ],
          "disabled": false,
          "omitted": false
        },
        {
          "id": "image",
          "name": "Image",
          "type": "Symbol",
          "localized": false,
          "required": false,
          "validations": [
          ],
          "disabled": false,
          "omitted": false
        },
        {
          "id": "comments",
          "name": "Comments",
          "type": "Array",
          "localized": false,
          "required": false,
          "validations": [
          ],
          "disabled": false,
          "omitted": false,
          "items": {
            "type": "Link",
            "validations": [
              {
                "linkContentType": [
                  "comment"
                ]
              }
            ],
            "linkType": "Entry"
          }
        },
        {
          "id": "likes",
          "name": "Likes",
          "type": "Array",
          "localized": false,
          "required": false,
          "validations": [
          ],
          "disabled": false,
          "omitted": false,
          "items": {
            "type": "Link",
            "validations": [
              {
                "linkContentType": [
                  "comment",
                  "post"
                ]
              }
            ],
            "linkType": "Entry"
          }
        }
      ]
    }
  ],
  "tags": [
  ],
  "editorInterfaces": [
    {
      "sys": {
        "id": "default",
        "type": "EditorInterface",
        "space": {
          "sys": {
            "id": "myhn7g87ffcm",
            "type": "Link",
            "linkType": "Space"
          }
        },
        "version": 18,
        "createdAt": "2024-08-22T23:35:33.237Z",
        "createdBy": {
          "sys": {
            "id": "69J9p6yQN9sFQFqs3m7Byv",
            "type": "Link",
            "linkType": "User"
          }
        },
        "updatedAt": "2024-08-23T00:00:06.936Z",
        "updatedBy": {
          "sys": {
            "id": "69J9p6yQN9sFQFqs3m7Byv",
            "type": "Link",
            "linkType": "User"
          }
        },
        "contentType": {
          "sys": {
            "id": "post",
            "type": "Link",
            "linkType": "ContentType"
          }
        },
        "environment": {
          "sys": {
            "id": "master",
            "type": "Link",
            "linkType": "Environment"
          }
        }
      },
      "controls": [
        {
          "fieldId": "title",
          "widgetId": "singleLine",
          "widgetNamespace": "builtin"
        },
        {
          "fieldId": "content",
          "widgetId": "richTextEditor",
          "widgetNamespace": "builtin"
        },
        {
          "fieldId": "likedBy",
          "widgetId": "entryLinksEditor",
          "widgetNamespace": "builtin"
        },
        {
          "fieldId": "comments",
          "widgetId": "entryLinksEditor",
          "widgetNamespace": "builtin"
        }
      ]
    },
    {
      "sys": {
        "id": "default",
        "type": "EditorInterface",
        "space": {
          "sys": {
            "id": "myhn7g87ffcm",
            "type": "Link",
            "linkType": "Space"
          }
        },
        "version": 8,
        "createdAt": "2024-08-22T23:37:51.906Z",
        "createdBy": {
          "sys": {
            "id": "69J9p6yQN9sFQFqs3m7Byv",
            "type": "Link",
            "linkType": "User"
          }
        },
        "updatedAt": "2024-08-22T23:58:59.914Z",
        "updatedBy": {
          "sys": {
            "id": "69J9p6yQN9sFQFqs3m7Byv",
            "type": "Link",
            "linkType": "User"
          }
        },
        "contentType": {
          "sys": {
            "id": "comment",
            "type": "Link",
            "linkType": "ContentType"
          }
        },
        "environment": {
          "sys": {
            "id": "master",
            "type": "Link",
            "linkType": "Environment"
          }
        }
      },
      "controls": [
        {
          "fieldId": "content",
          "widgetId": "richTextEditor",
          "widgetNamespace": "builtin"
        },
        {
          "fieldId": "author",
          "widgetId": "entryLinkEditor",
          "widgetNamespace": "builtin"
        },
        {
          "fieldId": "likedBy",
          "widgetId": "entryLinksEditor",
          "widgetNamespace": "builtin"
        }
      ]
    },
    {
      "sys": {
        "id": "default",
        "type": "EditorInterface",
        "space": {
          "sys": {
            "id": "myhn7g87ffcm",
            "type": "Link",
            "linkType": "Space"
          }
        },
        "version": 24,
        "createdAt": "2024-08-22T23:38:50.439Z",
        "createdBy": {
          "sys": {
            "id": "69J9p6yQN9sFQFqs3m7Byv",
            "type": "Link",
            "linkType": "User"
          }
        },
        "updatedAt": "2024-08-23T04:17:42.770Z",
        "updatedBy": {
          "sys": {
            "id": "69J9p6yQN9sFQFqs3m7Byv",
            "type": "Link",
            "linkType": "User"
          }
        },
        "contentType": {
          "sys": {
            "id": "user",
            "type": "Link",
            "linkType": "ContentType"
          }
        },
        "environment": {
          "sys": {
            "id": "master",
            "type": "Link",
            "linkType": "Environment"
          }
        }
      },
      "controls": [
        {
          "fieldId": "id",
          "widgetId": "singleLine",
          "widgetNamespace": "builtin"
        },
        {
          "fieldId": "name",
          "widgetId": "singleLine",
          "widgetNamespace": "builtin"
        },
        {
          "fieldId": "email",
          "widgetId": "singleLine",
          "widgetNamespace": "builtin"
        },
        {
          "fieldId": "image",
          "widgetId": "singleLine",
          "widgetNamespace": "builtin"
        },
        {
          "fieldId": "comments",
          "widgetId": "entryLinksEditor",
          "widgetNamespace": "builtin"
        },
        {
          "fieldId": "likes",
          "widgetId": "entryLinksEditor",
          "widgetNamespace": "builtin"
        }
      ]
    }
  ],
  "entries": [
  ],
  "assets": [
    {
      "metadata": {
        "tags": [
        ]
      },
      "sys": {
        "space": {
          "sys": {
            "type": "Link",
            "linkType": "Space",
            "id": "myhn7g87ffcm"
          }
        },
        "id": "7dPZ7ei06A2FKUSqaO4Ugb",
        "type": "Asset",
        "createdAt": "2023-08-19T15:45:07.418Z",
        "updatedAt": "2023-08-19T15:54:19.641Z",
        "environment": {
          "sys": {
            "id": "master",
            "type": "Link",
            "linkType": "Environment"
          }
        },
        "publishedVersion": 7,
        "publishedAt": "2023-08-19T15:54:19.641Z",
        "firstPublishedAt": "2023-08-19T15:47:24.390Z",
        "createdBy": {
          "sys": {
            "type": "Link",
            "linkType": "User",
            "id": "69J9p6yQN9sFQFqs3m7Byv"
          }
        },
        "updatedBy": {
          "sys": {
            "type": "Link",
            "linkType": "User",
            "id": "69J9p6yQN9sFQFqs3m7Byv"
          }
        },
        "publishedCounter": 2,
        "version": 8,
        "publishedBy": {
          "sys": {
            "type": "Link",
            "linkType": "User",
            "id": "69J9p6yQN9sFQFqs3m7Byv"
          }
        },
        "urn": "crn:contentful:::content:spaces/myhn7g87ffcm/environments/master/assets/7dPZ7ei06A2FKUSqaO4Ugb"
      },
      "fields": {
        "title": {
          "en-US": "Avianca"
        },
        "description": {
          "en-US": "Descripción aquí"
        },
        "file": {
          "en-US": {
            "url": "//images.ctfassets.net/myhn7g87ffcm/7dPZ7ei06A2FKUSqaO4Ugb/aa28c8974382035a2bde88f79f6f0a64/logo.png",
            "details": {
              "size": 1752,
              "image": {
                "width": 200,
                "height": 70
              }
            },
            "fileName": "logo.png",
            "contentType": "image/png"
          }
        }
      }
    }
  ],
  "locales": [
    {
      "name": "English (United States)",
      "code": "en-US",
      "fallbackCode": null,
      "default": true,
      "contentManagementApi": true,
      "contentDeliveryApi": true,
      "optional": false,
      "sys": {
        "type": "Locale",
        "id": "0Z0hKrSrgcOiSoLNg9HFTq",
        "version": 1,
        "space": {
          "sys": {
            "type": "Link",
            "linkType": "Space",
            "id": "myhn7g87ffcm"
          }
        },
        "environment": {
          "sys": {
            "type": "Link",
            "linkType": "Environment",
            "id": "master",
            "uuid": "45ecd43f-8464-45e9-a48a-58258451abca"
          }
        },
        "createdBy": {
          "sys": {
            "type": "Link",
            "linkType": "User",
            "id": "69J9p6yQN9sFQFqs3m7Byv"
          }
        },
        "createdAt": "2023-08-18T20:52:54Z",
        "updatedBy": {
          "sys": {
            "type": "Link",
            "linkType": "User",
            "id": "69J9p6yQN9sFQFqs3m7Byv"
          }
        },
        "updatedAt": "2023-08-18T20:52:54Z"
      }
    }
  ],
  "webhooks": [
    {
      "name": "Update",
      "url": "https://kiusys-poc.vercel.app/api/revalidate?path=/avianca-bogota-medellin",
      "httpBasicUsername": null,
      "topics": [
        "Entry.publish"
      ],
      "filters": null,
      "transformation": null,
      "active": true,
      "sys": {
        "type": "WebhookDefinition",
        "id": "2avc20sPyGb9rtnZZRzjx5",
        "version": 1,
        "space": {
          "sys": {
            "type": "Link",
            "linkType": "Space",
            "id": "myhn7g87ffcm"
          }
        },
        "createdBy": {
          "sys": {
            "type": "Link",
            "linkType": "User",
            "id": "69J9p6yQN9sFQFqs3m7Byv"
          }
        },
        "createdAt": "2023-09-21T13:04:10Z",
        "updatedBy": {
          "sys": {
            "type": "Link",
            "linkType": "User",
            "id": "69J9p6yQN9sFQFqs3m7Byv"
          }
        },
        "updatedAt": "2023-09-21T13:04:44Z"
      },
      "headers": [
      ]
    }
  ],
  "roles": [
    {
      "name": "Author",
      "description": "Allows editing of content",
      "policies": [
        {
          "effect": "allow",
          "actions": [
            "create"
          ],
          "constraint": {
            "and": [
              {
                "equals": [
                  {
                    "doc": "sys.type"
                  },
                  "Entry"
                ]
              }
            ]
          }
        },
        {
          "effect": "allow",
          "actions": [
            "read"
          ],
          "constraint": {
            "and": [
              {
                "equals": [
                  {
                    "doc": "sys.type"
                  },
                  "Entry"
                ]
              }
            ]
          }
        },
        {
          "effect": "allow",
          "actions": [
            "update"
          ],
          "constraint": {
            "and": [
              {
                "equals": [
                  {
                    "doc": "sys.type"
                  },
                  "Entry"
                ]
              }
            ]
          }
        },
        {
          "effect": "allow",
          "actions": [
            "create"
          ],
          "constraint": {
            "and": [
              {
                "equals": [
                  {
                    "doc": "sys.type"
                  },
                  "Asset"
                ]
              }
            ]
          }
        },
        {
          "effect": "allow",
          "actions": [
            "read"
          ],
          "constraint": {
            "and": [
              {
                "equals": [
                  {
                    "doc": "sys.type"
                  },
                  "Asset"
                ]
              }
            ]
          }
        },
        {
          "effect": "allow",
          "actions": [
            "update"
          ],
          "constraint": {
            "and": [
              {
                "equals": [
                  {
                    "doc": "sys.type"
                  },
                  "Asset"
                ]
              }
            ]
          }
        }
      ],
      "permissions": {
        "ContentModel": [
          "read"
        ],
        "Settings": [
        ],
        "ContentDelivery": [
        ],
        "Environments": [
        ],
        "EnvironmentAliases": [
        ],
        "Tags": [
        ]
      },
      "sys": {
        "type": "Role",
        "id": "0ZrRP6F7OleAFyuDkGKkhG",
        "version": 0,
        "space": {
          "sys": {
            "type": "Link",
            "linkType": "Space",
            "id": "myhn7g87ffcm"
          }
        },
        "createdBy": {
          "sys": {
            "type": "Link",
            "linkType": "User",
            "id": "69J9p6yQN9sFQFqs3m7Byv"
          }
        },
        "createdAt": "2023-08-18T20:52:54Z",
        "updatedBy": {
          "sys": {
            "type": "Link",
            "linkType": "User",
            "id": "69J9p6yQN9sFQFqs3m7Byv"
          }
        },
        "updatedAt": "2023-08-18T20:52:54Z"
      }
    },
    {
      "name": "Editor",
      "description": "Allows editing, publishing and archiving of content",
      "policies": [
        {
          "effect": "allow",
          "actions": "all",
          "constraint": {
            "and": [
              {
                "equals": [
                  {
                    "doc": "sys.type"
                  },
                  "Entry"
                ]
              }
            ]
          }
        },
        {
          "effect": "allow",
          "actions": "all",
          "constraint": {
            "and": [
              {
                "equals": [
                  {
                    "doc": "sys.type"
                  },
                  "Asset"
                ]
              }
            ]
          }
        }
      ],
      "permissions": {
        "ContentModel": [
          "read"
        ],
        "Settings": [
        ],
        "ContentDelivery": [
        ],
        "Environments": [
        ],
        "EnvironmentAliases": [
        ],
        "Tags": [
        ]
      },
      "sys": {
        "type": "Role",
        "id": "0ZsEXUciI9biB4e1xUzpWg",
        "version": 0,
        "space": {
          "sys": {
            "type": "Link",
            "linkType": "Space",
            "id": "myhn7g87ffcm"
          }
        },
        "createdBy": {
          "sys": {
            "type": "Link",
            "linkType": "User",
            "id": "69J9p6yQN9sFQFqs3m7Byv"
          }
        },
        "createdAt": "2023-08-18T20:52:54Z",
        "updatedBy": {
          "sys": {
            "type": "Link",
            "linkType": "User",
            "id": "69J9p6yQN9sFQFqs3m7Byv"
          }
        },
        "updatedAt": "2023-08-18T20:52:54Z"
      }
    },
    {
      "name": "Translator",
      "description": "Allows editing of localized fields in the specified language",
      "policies": [
        {
          "effect": "allow",
          "actions": [
            "read"
          ],
          "constraint": {
            "and": [
              {
                "equals": [
                  {
                    "doc": "sys.type"
                  },
                  "Entry"
                ]
              }
            ]
          }
        },
        {
          "effect": "allow",
          "actions": [
            "read"
          ],
          "constraint": {
            "and": [
              {
                "equals": [
                  {
                    "doc": "sys.type"
                  },
                  "Asset"
                ]
              }
            ]
          }
        },
        {
          "effect": "allow",
          "actions": [
            "update"
          ],
          "constraint": {
            "and": [
              {
                "equals": [
                  {
                    "doc": "sys.type"
                  },
                  "Entry"
                ]
              },
              {
                "paths": [
                  {
                    "doc": "fields.%.%"
                  }
                ]
              }
            ]
          }
        },
        {
          "effect": "allow",
          "actions": [
            "update"
          ],
          "constraint": {
            "and": [
              {
                "equals": [
                  {
                    "doc": "sys.type"
                  },
                  "Asset"
                ]
              },
              {
                "paths": [
                  {
                    "doc": "fields.%.%"
                  }
                ]
              }
            ]
          }
        }
      ],
      "permissions": {
        "ContentModel": [
          "read"
        ],
        "Settings": [
        ],
        "ContentDelivery": [
        ],
        "Environments": [
        ],
        "EnvironmentAliases": [
        ],
        "Tags": [
        ]
      },
      "sys": {
        "type": "Role",
        "id": "0Zt9hHYEB04lvtdSN2bpgs",
        "version": 0,
        "space": {
          "sys": {
            "type": "Link",
            "linkType": "Space",
            "id": "myhn7g87ffcm"
          }
        },
        "createdBy": {
          "sys": {
            "type": "Link",
            "linkType": "User",
            "id": "69J9p6yQN9sFQFqs3m7Byv"
          }
        },
        "createdAt": "2023-08-18T20:52:54Z",
        "updatedBy": {
          "sys": {
            "type": "Link",
            "linkType": "User",
            "id": "69J9p6yQN9sFQFqs3m7Byv"
          }
        },
        "updatedAt": "2023-08-18T20:52:54Z"
      }
    }
  ]
}